common/__init__.py
common/customException.py
common/debugTalk.py
common/operateRedis.py
common/operationConfig.py
common/paramsEncoder.py
common/readLog.py
common/setting.py
LJScript-1.0.dist-info/METADATA
LJScript-1.0.dist-info/WHEEL
LJScript-1.0.dist-info/top_level.txt
LJScript-1.0.dist-info/RECORD
